[
  {
    "company": "Amoda Iron & Steel Limited",
    "email": "secretarial@amodagroup.com",
    "region": "Telangana",
    "sector": "Steel Manufacturing",
    "message": "**Subject: Strengthening Amoda Iron & Steel\u2019s Environmental Compliance & Reporting Framework**\n\n***[Note: If sending via LinkedIn, please ensure the character count fits within the InMail limits. If sending via email, use the subject line above.]***\n\nDear [Name of Executive],\n\nAs the steel sector in India faces an increasingly complex regulatory landscape, maintaining transparency with the Telangana State Pollution Control Board (TSPCB) has become as critical to operational continuity as production output itself.\n\nMy team has been reviewing the current compliance landscape for the steel manufacturing sector in Telangana. We\u2019ve noted that while the industry continues to operate under the *Environment (Protection) Rules, 1986*, the pressure to align with site-specific Consent to Operate (CTO) conditions\u2014as managed via the OCMMS portal\u2014is intensifying. \n\nFurthermore, with the formal transition toward the **Indian Carbon Market (ICM)** and the introduction of sector-specific carbon intensity targets, the margin for error in emissions reporting is narrowing. We recognize that tracking unit-specific baselines dynamically against fluctuating regulatory requirements is a significant operational challenge for integrated steel plants.\n\nAt [Your Company Name], we specialize in helping heavy industry leaders bridge the gap between complex regulatory mandates and real-time operational data. Our platform automates the reconciliation of site-specific emission metrics against TSPCB-mandated limits, ensuring that your reporting is not only accurate but audit-ready at all times.\n\nI am reaching out to see if you would be open to a brief, 15-minute introductory call. I would like to showcase how our automated compliance platform handles dynamic intensity forecasting, specifically designed to help firms like Amoda Iron & Steel stay ahead of evolving ICM targets and maintain seamless compliance transparency.\n\nDo you have any availability next [Day of the week] for a brief conversation?\n\nBest regards,\n\n[Your Name]\n[Your Title]\n[Your Company Name]\n[Your Phone Number]\n[Link to Website/Case Study]\n\n***\n\n*Disclaimer: This outreach is intended for informational purposes regarding regulatory compliance trends. Our analysis of compliance status is based on publicly available reporting data and is intended to assist in proactive risk management.*",
    "source": "frontend_approval",
    "notified_at": "2026-06-27T13:43:18.246009Z"
  },
  {
    "company": "Arjas Steel Private Limited",
    "email": "contact@arjas.com",
    "region": "Andhra Pradesh",
    "sector": "Steel Manufacturing",
    "message": "**Subject:** Proactive Compliance Strategy: Adapting to evolving MoEFCC standards at Arjas Steel\n\n*(Note: If you do not have a direct email address, this message is structured for a high-impact LinkedIn InMail/Connection request.)*\n\n***\n\n**Dear [Executive Name/Leadership Team],**\n\nAs the steel manufacturing sector in India navigates the transition toward more stringent environmental oversight, the complexity of aligning facility-level operations with shifting regulatory benchmarks has become a strategic priority for industry leaders.\n\nWith the recent issuance of **MoEFCC Notification GSR 85(E)** and the ongoing evolution of the **Indian Carbon Market (ICM)**, the regulatory landscape is shifting from static reporting to dynamic intensity targets. For integrated manufacturers like Arjas Steel, the challenge lies in reconciling the specific numeric limits stipulated in your **Consent to Operate (CTO)** with these emerging national intensity frameworks.\n\nWe have been observing that many firms in the sector are finding it increasingly difficult to track unit-specific emission baselines in real-time. Without a centralized, automated mechanism to bridge the gap between facility-level sensor data and these evolving compliance mandates, maintaining audit-readiness becomes an operational bottleneck rather than a competitive advantage.\n\nOur platform specializes in automating this complexity. We help heavy industry leaders:\n*   **Centralize Compliance:** Automatically map real-time emission metrics against your specific CTO limits and national standards.\n*   **Forecast Intensity:** Provide dynamic modeling to help you stay ahead of the Indian Carbon Market\u2019s upcoming intensity-based targets.\n*   **Audit-Proof Operations:** Maintain a verifiable, audit-ready data trail that simplifies reporting to the APPCB and national regulators.\n\nI would welcome the opportunity to share a brief overview of how we are helping steel manufacturers transform their compliance posture from reactive to predictive. \n\nDo you have 15 minutes next Tuesday or Wednesday for a brief introductory call to discuss how your team is approaching these 2025/2026 regulatory benchmarks?\n\nBest regards,\n\n[Your Name]\n[Your Title]\n[Your Company Name]\n[Your Phone Number/Website]\n\n***\n\n*Disclaimer: This communication is intended for informational purposes regarding compliance technology. We recommend that all specific facility-level limits be verified directly through the Andhra Pradesh Pollution Control Board (APPCB) official portal.*",
    "source": "frontend_approval",
    "notified_at": "2026-06-27T15:09:06.612257Z"
  }
]